qkup/__init__.py
qkup/uploader.py
qkup-0.0.1.dist-info/METADATA
qkup-0.0.1.dist-info/WHEEL
qkup-0.0.1.dist-info/entry_points.txt
qkup-0.0.1.dist-info/top_level.txt
qkup-0.0.1.dist-info/RECORD
