Metadata-Version: 2.2
Name: qkup
Version: 0.0.1
Summary: 一个简单的命令行 FTP 上传工具
Home-page: https://github.com/lysdgit/qkup
Author: lysder
Author-email: lysder@qq.com
Classifier: Programming Language :: Python :: 3
Classifier: License :: OSI Approved :: MIT License
Classifier: Operating System :: OS Independent
Requires-Python: >=3.6
Dynamic: author
Dynamic: author-email
Dynamic: classifier
Dynamic: description-content-type
Dynamic: home-page
Dynamic: requires-python
Dynamic: summary
